local_qwen3b_part028/__init__.py
local_qwen3b_part028/qwen2.5-3b-instruct-q5_k_m.gguf.part_028
local_qwen3b_part028-0.0.1.dist-info/METADATA
local_qwen3b_part028-0.0.1.dist-info/WHEEL
local_qwen3b_part028-0.0.1.dist-info/top_level.txt
local_qwen3b_part028-0.0.1.dist-info/RECORD
